Workbook

Sheet Fiche
A1: FICHE DE PERSONNAGE — Hunter × Hunter (JDR)
A2: Légende : cellules BLANCHES = à remplir (saisie) ; cellules BEIGES = calculées automatiquement (ne pas écrire dedans).
A4: 1 · Identité
A5: Nom | B5: Gon | F5: Classe | G5: Combattant
A6: Éclat | B6: 10 | C6: Palier d'Éclat | D6: =5*ROUNDDOWN(B6/5,0) | F6: Plafond carac | G6: =VLOOKUP(B6,Barèmes!$A$39:$B$44,2,TRUE)
A7: PF total | B7: 100 | C7: Niveau | D7: =ROUNDUP(B7/100,0) | F7: PV max | G7: =100*D7
A8: DI total | B8: 0 | C8: Prestige | D8: =ROUNDUP(B8/100,0) | F8: PV courants | G8: 100
A9: Arme (bonus de classe) | B9: Armes de mêlée | F9: Défense (bonus de classe) | G9: Esquive
A10: Bonus de classe du Combattant (+10 d'office) : Initiative, Lutte, Résistance à la douleur, l'arme choisie ci-dessus et la défense choisie ci-dessus. Reportés dans la colonne Bonus des compétences.
A12: 1 bis · Plafonds de formation (Combattant)
A13: Champ | B13: Plafond % | C13: PF max | F13: Champ | G13: Plafond % | H13: PF max | K13: Champ | L13: Plafond % | M13: PF max
A14: Martial | B14: 40 | C14: =ROUNDDOWN(B14*$B$7/100,0) | F14: Intellectuel | G14: 10 | H14: =ROUNDDOWN(G14*$B$7/100,0) | K14: Transport | L14: 20 | M14: =ROUNDDOWN(L14*$B$7/100,0)
A15: Athlétique | B15: 30 | C15: =ROUNDDOWN(B15*$B$7/100,0) | F15: Naturel | G15: 20 | H15: =ROUNDDOWN(G15*$B$7/100,0) | K15: Furtif | L15: 20 | M15: =ROUNDDOWN(L15*$B$7/100,0)
A16: Vital | B16: 30 | C16: =ROUNDDOWN(B16*$B$7/100,0) | F16: Sensoriel | G16: 20 | H16: =ROUNDDOWN(G16*$B$7/100,0) | K16: Artisanal | L16: 10 | M16: =ROUNDDOWN(L16*$B$7/100,0)
A17: Social | B17: 10 | C17: =ROUNDDOWN(B17*$B$7/100,0) | F17: Technique | G17: 10 | H17: =ROUNDDOWN(G17*$B$7/100,0) | K17: Artistique | L17: 10 | M17: =ROUNDDOWN(L17*$B$7/100,0)
A18: Arts martiaux et formations comptent dans le champ Martial. Le plafond s'applique aux PF totaux, et s'élève donc avec le niveau.
A20: 2 · Caractéristiques (saisie 0–30, ≤ plafond)
A21: Physique | B21: Valeur | C21: MOD | D21: Plafond | F21: Mentale | G21: Valeur | H21: MOD | I21: Plafond | K21: Point buy — création | P21: (aux. coût point-buy par carac)
A22: FOR — Force | B22: 5 | C22: =VLOOKUP(B22,Barèmes!$A$5:$B$35,2,FALSE) | D22: =$G$6 | F22: VOL — Volonté | G22: 5 | H22: =VLOOKUP(G22,Barèmes!$A$5:$B$35,2,FALSE) | I22: =$G$6 | K22: Moyenne | L22: =VLOOKUP($B$6,Barèmes!$A$48:$D$51,2,TRUE) | M22: Plafond | N22: =VLOOKUP($B$6,Barèmes!$A$48:$D$51,3,TRUE) | P22: =IF(B22<=$L$22,B22-3,($L$22-3)+(B22-$L$22)*(B22-$L$22+3)/2) | Q22: =IF(G22<=$L$22,G22-3,($L$22-3)+(G22-$L$22)*(G22-$L$22+3)/2)
A23: DEX — Dextérité | B23: 5 | C23: =VLOOKUP(B23,Barèmes!$A$5:$B$35,2,FALSE) | D23: =$G$6 | F23: LOG — Logique | G23: 5 | H23: =VLOOKUP(G23,Barèmes!$A$5:$B$35,2,FALSE) | I23: =$G$6 | K23: Budget | L23: =VLOOKUP($B$6,Barèmes!$A$48:$D$51,4,TRUE) | M23: Coût | N23: =SUM(P22:P27)+SUM(Q22:Q27) | P23: =IF(B23<=$L$22,B23-3,($L$22-3)+(B23-$L$22)*(B23-$L$22+3)/2) | Q23: =IF(G23<=$L$22,G23-3,($L$22-3)+(G23-$L$22)*(G23-$L$22+3)/2)
A24: AGI — Agilité | B24: 5 | C24: =VLOOKUP(B24,Barèmes!$A$5:$B$35,2,FALSE) | D24: =$G$6 | F24: INS — Instinct | G24: 5 | H24: =VLOOKUP(G24,Barèmes!$A$5:$B$35,2,FALSE) | I24: =$G$6 | K24: Reste | L24: =L23-N23 | M24: > plafond ? | N24: =IF(MAX(B22:B27,G22:G27)>N22,"oui","non") | P24: =IF(B24<=$L$22,B24-3,($L$22-3)+(B24-$L$22)*(B24-$L$22+3)/2) | Q24: =IF(G24<=$L$22,G24-3,($L$22-3)+(G24-$L$22)*(G24-$L$22+3)/2)
A25: END — Endurance | B25: 5 | C25: =VLOOKUP(B25,Barèmes!$A$5:$B$35,2,FALSE) | D25: =$G$6 | F25: ÉRU — Érudition | G25: 5 | H25: =VLOOKUP(G25,Barèmes!$A$5:$B$35,2,FALSE) | I25: =$G$6 | P25: =IF(B25<=$L$22,B25-3,($L$22-3)+(B25-$L$22)*(B25-$L$22+3)/2) | Q25: =IF(G25<=$L$22,G25-3,($L$22-3)+(G25-$L$22)*(G25-$L$22+3)/2)
A26: PER — Perception | B26: 5 | C26: =VLOOKUP(B26,Barèmes!$A$5:$B$35,2,FALSE) | D26: =$G$6 | F26: IMA — Imagination | G26: 5 | H26: =VLOOKUP(G26,Barèmes!$A$5:$B$35,2,FALSE) | I26: =$G$6 | P26: =IF(B26<=$L$22,B26-3,($L$22-3)+(B26-$L$22)*(B26-$L$22+3)/2) | Q26: =IF(G26<=$L$22,G26-3,($L$22-3)+(G26-$L$22)*(G26-$L$22+3)/2)
A27: PRÉ — Présence | B27: 5 | C27: =VLOOKUP(B27,Barèmes!$A$5:$B$35,2,FALSE) | D27: =$G$6 | F27: CHA — Charisme | G27: 5 | H27: =VLOOKUP(G27,Barèmes!$A$5:$B$35,2,FALSE) | I27: =$G$6 | P27: =IF(B27<=$L$22,B27-3,($L$22-3)+(B27-$L$22)*(B27-$L$22+3)/2) | Q27: =IF(G27<=$L$22,G27-3,($L$22-3)+(G27-$L$22)*(G27-$L$22+3)/2)
A28: Total caractéristiques | B28: =SUM(B22,B23,B24,B25,B26,B27,G22,G23,G24,G25,G26,G27) | C28: Repère : 5 moyenne · 9 max humain · 19 sommet · 30 au-delà
A30: 3 · Capacités physiques
A31: Actions actives / tour | B31: =MAX(1,MIN(10,ROUNDDOWN((C24+C23)/10,0))) | D31: Taille | E31: Moyenne | H31: Espace / Allonge | I31: 1 m / 1 m (Moyenne)
A32: Capacité | B32: Légère | C32: Intermédiaire | D32: Lourde | F32: Capacité | G32: Légère | H32: Intermédiaire | I32: Lourde
A33: Mouvement | B33: =VLOOKUP(B24,Barèmes!$A$89:$D$119,2,FALSE) | C33: =VLOOKUP(B24,Barèmes!$A$89:$D$119,3,FALSE) | D33: =VLOOKUP(B24,Barèmes!$A$89:$D$119,4,FALSE) | F33: Indice de poids | G33: =VLOOKUP(B22,Barèmes!$A$55:$D$85,2,FALSE) | H33: =VLOOKUP(B22,Barèmes!$A$55:$D$85,3,FALSE) | I33: =VLOOKUP(B22,Barèmes!$A$55:$D$85,4,FALSE)
A34: Apnée | B34: =VLOOKUP(B25,Barèmes!$A$123:$D$153,2,FALSE) | C34: =VLOOKUP(B25,Barèmes!$A$123:$D$153,3,FALSE) | D34: =VLOOKUP(B25,Barèmes!$A$123:$D$153,4,FALSE) | F34: Tirer / pousser | G34: =indice de poids × 10 (chaque colonne)
A35: Suffocation | B35: =B25 | C35: rounds avant inconscience ; mort à 2 × END | F35: Mort (suffocation) | G35: =2*B25 | H35: rounds (pleine respiration → mort)
A37: 4 · Combat
A38: Actions actives / tour | B38: =$B$31 | D38: PV max | E38: =$G$7 | G38: PV courants | H38: =$G$8
A40: Réduction de dégâts (armure) | B40: CON | C40: TRA | D40: PER | E40: FEU | F40: FRO | G40: ÉLE | H40: DÉC
B41: 0 | C41: 0 | D41: 0 | E41: 0 | F41: 0 | G41: 0 | H41: 0
A42: Jets de combat — Initiative, attaque avec l'arme (Armes de mêlée / jet / Archerie / feu), Parade, Esquive, Lutte : voir la section Compétences.
A44: Arme équipée | B44: Nom | C44: Dégâts faciaux | D44: Mult. N (0–3) | F44: Finesse | G44: Type | H44: Dégâts de base
B45: Mains nues | C45: 20 | D45: 1 | F45: Non | G45: CON | H45: =C45+D45*IF(F45="Oui",C23,C22)
A46: Dégâts infligés = (Dégâts de base − réduction de dégâts du type) × marge% ; la réduction se retire avant le multiplicateur.
A48: 5 · Aura & Nen
A49: Archétype | B49: Renforceur | D49: Avantage Spécialiste | F49: Non | H49: DI total | I49: =$B$8
A50: Affinité | B50: Renf. | C50: Émis. | D50: Transm. | F50: Manip. | G50: Conj. | H50: Spé.
A51: Affinité (%) | B51: =VLOOKUP(B49,Barèmes!$A$157:$H$168,2,FALSE) | C51: =VLOOKUP(B49,Barèmes!$A$157:$H$168,3,FALSE) | D51: =VLOOKUP(B49,Barèmes!$A$157:$H$168,4,FALSE) | F51: =VLOOKUP(B49,Barèmes!$A$157:$H$168,5,FALSE) | G51: =VLOOKUP(B49,Barèmes!$A$157:$H$168,6,FALSE) | H51: =IF(F49="Oui",VLOOKUP(B49,Barèmes!$A$157:$H$168,8,FALSE),VLOOKUP(B49,Barèmes!$A$157:$H$168,7,FALSE))
A53: Aura | B53: Base | C53: Mult. | D53: Valeur | F53: Réserve | G53: Valeur
A54: UAR (par round) | B54: 5 | C54: 0 | D54: =B54*(C54+1) | F54: UAM (aura max) | G54: =100*$D$8+20*G55
A55: RUA (par heure) | B55: 5 | C55: 0 | D55: =B55*(C55+1) | F55: Achats UAM (tranches) | G55: 0
A56: Prestige (rappel) | B56: =$D$8 | C56: UAD courant | D56: 100 | F56: UAD ≤ UAM ; remonte de la RUA chaque heure.
A58: Conversion DI → catégorie
A59: Catégorie | B59: DI investi | C59: Affinité % | D59: Points (DX) | F59: Catégorie | G59: DI investi | H59: Affinité % | I59: Points (DX)
A60: DR (Renforcement) | B60: 0 | C60: =B51 | D60: =ROUNDDOWN(B60*B51/100,0) | F60: DM (Manipulation) | G60: 0 | H60: =F51 | I60: =ROUNDDOWN(G60*F51/100,0)
A61: DE (Émission) | B61: 0 | C61: =C51 | D61: =ROUNDDOWN(B61*C51/100,0) | F61: DC (Conjuration) | G61: 0 | H61: =G51 | I61: =ROUNDDOWN(G61*G51/100,0)
A62: DT (Transmutation) | B62: 0 | C62: =D51 | D62: =ROUNDDOWN(B62*D51/100,0) | F62: DS (Spécialisation) | G62: 0 | H62: =H51 | I62: =ROUNDDOWN(G62*H51/100,0)
A64: 6 · Techniques du Nen
A65: Technique (bloc) | B65: Possédée | C65: Coût DI | F65: État (palier) | G65: Palier | H65: Coût DI cumulé
A66: Initiation | B66: Oui | C66: =IF(B66="Oui",40,0) | F66: Ten | G66: Aucun | H66: =INDEX(Barèmes!$A$172:$F$178,MATCH("Ten",Barèmes!$A$172:$A$178,0),MATCH(G66,{"Aucun","Basique","Avancé","Expert","Maître"},0)+1)
A67: Hatsu | B67: Non | C67: =IF(B67="Oui",30,0) | F67: Zetsu | G67: Aucun | H67: =INDEX(Barèmes!$A$172:$F$178,MATCH("Zetsu",Barèmes!$A$172:$A$178,0),MATCH(G67,{"Aucun","Basique","Avancé","Expert","Maître"},0)+1)
A68: Gyo | B68: Non | C68: =IF(B68="Oui",20,0) | F68: Ren | G68: Aucun | H68: =INDEX(Barèmes!$A$172:$F$178,MATCH("Ren",Barèmes!$A$172:$A$178,0),MATCH(G68,{"Aucun","Basique","Avancé","Expert","Maître"},0)+1)
A69: Shu | B69: Non | C69: =IF(B69="Oui",20,0) | F69: Ken | G69: Aucun | H69: =INDEX(Barèmes!$A$172:$F$178,MATCH("Ken",Barèmes!$A$172:$A$178,0),MATCH(G69,{"Aucun","Basique","Avancé","Expert","Maître"},0)+1)
A70: In | B70: Non | C70: =IF(B70="Oui",30,0) | F70: En | G70: Aucun | H70: =INDEX(Barèmes!$A$172:$F$178,MATCH("En",Barèmes!$A$172:$A$178,0),MATCH(G70,{"Aucun","Basique","Avancé","Expert","Maître"},0)+1)
F71: Ko | G71: Aucun | H71: =INDEX(Barèmes!$A$172:$F$178,MATCH("Ko",Barèmes!$A$172:$A$178,0),MATCH(G71,{"Aucun","Basique","Avancé","Expert","Maître"},0)+1)
F72: Ryu | G72: Aucun | H72: =INDEX(Barèmes!$A$172:$F$178,MATCH("Ryu",Barèmes!$A$172:$A$178,0),MATCH(G72,{"Aucun","Basique","Avancé","Expert","Maître"},0)+1)
A74: DI dépensé en techniques | B74: =SUM(C66,C67,C68,C69,C70,H66,H67,H68,H69,H70,H71,H72) | F74: Base d'UAR conférée par l'état à manteau actif (Ren/Ken/Ko/Ryu) : Basique 10 · Avancé 15 · Expert 20 · Maître 25.
A76: 7 · Compétences (Bonus = Valeur + MOD de la carac liée)
A77: Champ Martial | F77: Champ Social | K77: Champ Intellectuel
A78: Compétence | B78: Carac | C78: Valeur | D78: Bonus | F78: Compétence | G78: Carac | H78: Valeur | I78: Bonus | K78: Compétence | L78: Carac | M78: Valeur | N78: Bonus
A79: Initiative | B79: AGI | C79: 0 | D79: =C79+C24+10 | F79: Persuasion | G79: CHA | H79: 0 | I79: =H79+H27 | K79: Histoire | L79: ÉRU | M79: 0 | N79: =M79+H25
A80: Armes de mêlée | B80: DEX | C80: 0 | D80: =C80+C23+IF($B$9="Armes de mêlée",10,0) | F80: Rhétorique | G80: CHA | H80: 0 | I80: =H80+H27 | K80: Archéologie | L80: ÉRU | M80: 0 | N80: =M80+H25
A81: Armes de jet | B81: DEX | C81: 0 | D81: =C81+C23+IF($B$9="Armes de jet",10,0) | F81: Négociation | G81: CHA | H81: 0 | I81: =H81+H27 | K81: Géographie | L81: ÉRU | M81: 0 | N81: =M81+H25
A82: Archerie | B82: DEX | C82: 0 | D82: =C82+C23+IF($B$9="Archerie",10,0) | F82: Tromperie | G82: CHA | H82: 0 | I82: =H82+H27 | K82: Cartographie | L82: LOG | M82: 0 | N82: =M82+H23
A83: Armes à feu | B83: DEX | C83: 0 | D83: =C83+C23+IF($B$9="Armes à feu",10,0) | F83: Séduction | G83: CHA | H83: 0 | I83: =H83+H27 | K83: Économie | L83: ÉRU | M83: 0 | N83: =M83+H25
A84: Parade | B84: DEX | C84: 0 | D84: =C84+C23+IF($G$9="Parade",10,0) | F84: Intimidation | G84: PRÉ | H84: 0 | I84: =H84+C27 | K84: Estimation | L84: ÉRU | M84: 0 | N84: =M84+H25
A85: Esquive | B85: AGI | C85: 0 | D85: =C85+C24+IF($G$9="Esquive",10,0) | F85: Interrogatoire | G85: CHA | H85: 0 | I85: =H85+H27 | K85: Politique | L85: ÉRU | M85: 0 | N85: =M85+H25
F86: Commandement | G86: PRÉ | H86: 0 | I86: =H86+C27 | K86: Droit | L86: ÉRU | M86: 0 | N86: =M86+H25
A87: Champ Athlétique | F87: Pédagogie | G87: ÉRU | H87: 0 | I87: =H87+H25 | K87: Langues | L87: ÉRU | M87: 0 | N87: =M87+H25
A88: Compétence | B88: Carac | C88: Valeur | D88: Bonus | F88: Relation | G88: CHA | H88: 0 | I88: =H88+H27 | K88: Astronomie | L88: ÉRU | M88: 0 | N88: =M88+H25
A89: Course | B89: AGI | C89: 0 | D89: =C89+C24 | F89: Étiquette | G89: ÉRU | H89: 0 | I89: =H89+H25 | K89: Architecture | L89: ÉRU | M89: 0 | N89: =M89+H25
A90: Saut | B90: AGI | C90: 0 | D90: =C90+C24 | F90: Style | G90: PRÉ | H90: 0 | I90: =H90+C27 | K90: Géologie | L90: ÉRU | M90: 0 | N90: =M90+H25
A91: Natation | B91: AGI | C91: 0 | D91: =C91+C24 | K91: Biologie | L91: ÉRU | M91: 0 | N91: =M91+H25
A92: Escalade | B92: AGI | C92: 0 | D92: =C92+C24 | F92: Champ Naturel | K92: Faune | L92: ÉRU | M92: 0 | N92: =M92+H25
A93: Équilibre | B93: AGI | C93: 0 | D93: =C93+C24 | F93: Compétence | G93: Carac | H93: Valeur | I93: Bonus | K93: Flore | L93: ÉRU | M93: 0 | N93: =M93+H25
A94: Contorsion | B94: AGI | C94: 0 | D94: =C94+C24 | F94: Survie | G94: INS | H94: 0 | I94: =H94+H24 | K94: Météorologie | L94: ÉRU | M94: 0 | N94: =M94+H25
A95: Chute | B95: AGI | C95: 0 | D95: =C95+C24 | F95: Pistage | G95: INS | H95: 0 | I95: =H95+H24 | K95: Mémorisation | L95: ÉRU | M95: 0 | N95: =M95+H25
A96: Lutte | B96: FOR | C96: 0 | D96: =C96+C22+10 | F96: Chasse | G96: INS | H96: 0 | I96: =H96+H24 | K96: Occultisme | L96: ÉRU | M96: 0 | N96: =M96+H25
A97: Prouesse de Force | B97: FOR | C97: 0 | D97: =C97+C22 | F97: Pêche | G97: INS | H97: 0 | I97: =H97+H24 | K97: Théologie | L97: ÉRU | M97: 0 | N97: =M97+H25
A98: Apnée | B98: END | C98: 0 | D98: =C98+C25 | F98: Dressage | G98: INS | H98: 0 | I98: =H98+H24 | K98: Médecine | L98: ÉRU | M98: 0 | N98: =M98+H25
F99: Élevage | G99: ÉRU | H99: 0 | I99: =H99+H25 | K99: Enquête | L99: LOG | M99: 0 | N99: =M99+H23
A100: Champ Vital | F100: Agriculture | G100: ÉRU | H100: 0 | I100: =H100+H25 | K100: Psychologie | L100: ÉRU | M100: 0 | N100: =M100+H25
A101: Compétence | B101: Carac | C101: Valeur | D101: Bonus | K101: Perspicacité | L101: INS | M101: 0 | N101: =M101+H24
A102: Résistance aux Maladies | B102: END | C102: 0 | D102: =C102+C25 | F102: Champ Artisanal | K102: Tactique | L102: LOG | M102: 0 | N102: =M102+H23
A103: Résistance aux Toxines | B103: END | C103: 0 | D103: =C103+C25 | F103: Compétence | G103: Carac | H103: Valeur | I103: Bonus | K103: Jeu d'argent | L103: LOG | M103: 0 | N103: =M103+H23
A104: Résistance à la douleur | B104: VOL | C104: 0 | D104: =C104+H22+10 | F104: Forge / Métallurgie | G104: DEX | H104: 0 | I104: =H104+C23 | K104: Jeux de stratégie | L104: LOG | M104: 0 | N104: =M104+H23
A105: Résistance à l'Environnement | B105: END | C105: 0 | D105: =C105+C25 | F105: Travail du bois | G105: DEX | H105: 0 | I105: =H105+C23
A106: Résistance à la Fatigue | B106: END | C106: 0 | D106: =C106+C25 | F106: Travail de la pierre | G106: DEX | H106: 0 | I106: =H106+C23 | K106: Champ Sensoriel
A107: Résistance Mentale | B107: VOL | C107: 0 | D107: =C107+H22 | F107: Textile | G107: DEX | H107: 0 | I107: =H107+C23 | K107: Compétence | L107: Carac | M107: Valeur | N107: Bonus
F108: Travail du cuir | G108: DEX | H108: 0 | I108: =H108+C23 | K108: Vue | L108: PER | M108: 0 | N108: =M108+C26
A109: Champ Furtif | F109: Poterie | G109: DEX | H109: 0 | I109: =H109+C23 | K109: Ouïe | L109: PER | M109: 0 | N109: =M109+C26
A110: Compétence | B110: Carac | C110: Valeur | D110: Bonus | F110: Verre | G110: DEX | H110: 0 | I110: =H110+C23 | K110: Odorat | L110: PER | M110: 0 | N110: =M110+C26
A111: Discrétion | B111: AGI | C111: 0 | D111: =C111+C24 | F111: Joaillerie | G111: DEX | H111: 0 | I111: =H111+C23 | K111: Goût | L111: PER | M111: 0 | N111: =M111+C26
A112: Camouflage | B112: DEX | C112: 0 | D112: =C112+C23 | F112: Cuisine | G112: DEX | H112: 0 | I112: =H112+C23 | K112: Toucher | L112: PER | M112: 0 | N112: =M112+C26
A113: Filature | B113: PER | C113: 0 | D113: =C113+C26 | F113: Brasserie & distillation | G113: ÉRU | H113: 0 | I113: =H113+H25 | K113: Chémesthésie | L113: INS | M113: 0 | N113: =M113+H24
...

Sheet Barèmes
A1: BARÈMES — tables de correspondance (feuille de calcul, ne pas modifier)
A3: MOD carac (valeur 0–30 → modificateur)
A4: Valeur | B4: MOD
A5: 0 | B5: -25
A6: 1 | B6: -20
A7: 2 | B7: -15
A8: 3 | B8: -10
A9: 4 | B9: -5
A10: 5 | B10: 0
A11: 6 | B11: 5
A12: 7 | B12: 5
A13: 8 | B13: 5
A14: 9 | B14: 5
A15: 10 | B15: 10
A16: 11 | B16: 10
... A35: 30 | B35: 50
A37: Plafond carac par Éclat
A38: Éclat ≥ | B38: Plafond
A39: 0 | B39: 9
A40: 10 | B40: 14
A41: 20 | B41: 19
A42: 30 | B42: 24
A43: 40 | B43: 29
A44: 50 | B44: 30
A46: Création par Éclat (moyenne / plafond / budget)
A47: Éclat ≥ | B47: Moyenne | C47: Plafond | D47: Budget
A48: 0 | B48: 5 | C48: 7 | D48: 24
A49: 15 | B49: 7 | C49: 9 | D49: 48
A50: 30 | B50: 9 | C50: 11 | D50: 72
A51: 45 | B51: 11 | C51: 13 | D51: 96
A53: Indice de poids (FOR → Légère / Inter / Lourde)
A54: FOR | B54: Légère | C54: Intermédiaire | D54: Lourde
A55: 0 | B55: 0 kg | C55: 0 kg | D55: 0 kg
A56: 1 | B56: 1 kg | C56: 2 kg | D56: 5 kg
A57: 2 | B57: 2 kg | C57: 5 kg | D57: 10 kg
A58: 3 | B58: 3 kg | C58: 8 kg | D58: 20 kg
A59: 4 | B59: 5 kg | C59: 15 kg | D59: 50 kg
A60: 5 | B60: 10 kg | C60: 30 kg | D60: 100 kg
A61: 6 | B61: 20 kg | C61: 60 kg | D61: 200 kg
A62: 7 | B62: 30 kg | C62: 100 kg | D62: 300 kg
A63: 8 | B63: 50 kg | C63: 150 kg | D63: 500 kg
A64: 9 | B64: 100 kg | C64: 300 kg | D64: 1 t
A65: 10 | B65: 1 t | C65: 3 t | D65: 10 t
A66: 11 | B66: 2 t | C66: 6 t | D66: 20 t
... A85: 30 | B85: 100M t | C85: 300M t | D85: 1 000M t
A87: Mouvement (AGI → Légère / Inter / Lourde, par round)
A88: AGI | B88: Légère | C88: Intermédiaire | D88: Lourde
A89: 0 | B89: 0 m | C89: 0 m | D89: 0 m
A90: 1 | B90: 2 m | C90: 4 m | D90: 10 m
A91: 2 | B91: 3 m | C91: 6 m | D91: 15 m
A92: 3 | B92: 4 m | C92: 8 m | D92: 20 m
A93: 4 | B93: 6 m | C93: 12 m | D93: 30 m
A94: 5 | B94: 8 m | C94: 16 m | D94: 40 m
A95: 6 | B95: 10 m | C95: 20 m | D95: 50 m
A96: 7 | B96: 12 m | C96: 24 m | D96: 60 m
A97: 8 | B97: 14 m | C97: 28 m | D97: 70 m
A98: 9 | B98: 16 m | C98: 32 m | D98: 80 m
A99: 10 | B99: 20 m | C99: 40 m | D99: 100 m
A100: 11 | B100: 30 m | C100: 60 m | D100: 150 m
... A119: 30 | B119: 100 km | C119: 200 km | D119: 500 km
A121: Apnée (END → Légère / Inter / Lourde)
A122: END | B122: Légère | C122: Intermédiaire | D122: Lourde
A123: 0 | B123: <6 s | C123: 0 s | D123: 0 s
A124: 1 | B124: 6 s | C124: <6 s | D124: 0 s
A125: 2 | B125: 12 s | C125: 6 s | D125: <6 s
A126: 3 | B126: 18 s | C126: 12 s | D126: 6 s
A127: 4 | B127: 30 s | C127: 18 s | D127: 12 s
A128: 5 | B128: 1 min | C128: 30 s | D128: 18 s
A129: 6 | B129: 2 min | C129: 1 min | D129: 30 s
A130: 7 | B130: 3 min | C130: 2 min | D130: 1 min
A131: 8 | B131: 5 min | C131: 3 min | D131: 2 min
A132: 9 | B132: 10 min | C132: 5 min | D132: 3 min
A133: 10 | B133: 20 min | C133: 10 min | D133: 5 min
A134: 11 | B134: 30 min | C134: 20 min | D134: 10 min
... A153: 30 | B153: illimitée | C153: illimitée | D153: illimitée
A155: Affinités par archétype (%) — G = Spé sans Spécialiste, H = Spé avec
A156: Archétype | B156: Renforcement | C156: Émission | D156: Transmutation | E156: Manipulation | F156: Conjuration | G156: Spé (sans) | H156: Spé (avec)
A157: Renforceur | B157: 100 | C157: 80 | D157: 80 | E157: 60 | F157: 60 | G157: 0 | H157: 40
A158: Émitteur | B158: 80 | C158: 100 | D158: 60 | E158: 80 | F158: 40 | G158: 0 | H158: 60
A159: Transmuteur | B159: 80 | C159: 60 | D159: 100 | E159: 40 | F159: 80 | G159: 0 | H159: 60
A160: Manipulateur | B160: 60 | C160: 80 | D160: 40 | E160: 100 | F160: 60 | G160: 0 | H160: 80
A161: Conjurateur | B161: 60 | C161: 40 | D161: 80 | E161: 60 | F161: 100 | G161: 0 | H161: 80
A162: Spécialiste | B162: 40 | C162: 60 | D162: 60 | E162: 80 | F162: 80 | G162: 0 | H162: 100
A163: Renforceur-Émitteur | B163: 90 | C163: 90 | D163: 70 | E163: 70 | F163: 50 | G163: 0 | H163: 50
A164: Renforceur-Transmuteur | B164: 90 | C164: 70 | D164: 90 | E164: 50 | F164: 70 | G164: 0 | H164: 50
A165: Émitteur-Manipulateur | B165: 70 | C165: 90 | D165: 50 | E165: 90 | F165: 50 | G165: 0 | H165: 70
A166: Transmuteur-Conjurateur | B166: 70 | C166: 50 | D166: 90 | E166: 50 | F166: 90 | G166: 0 | H166: 70
A167: Manipulateur-Spécialiste | B167: 50 | C167: 70 | D167: 50 | E167: 90 | F167: 70 | G167: 0 | H167: 90
A168: Conjurateur-Spécialiste | B168: 50 | C168: 50 | D168: 70 | E168: 70 | F168: 90 | G168: 0 | H168: 90
A170: Coûts DI des techniques (cumulés par palier)
A171: Technique | B171: Aucun | C171: Basique | D171: Avancé | E171: Expert | F171: Maître
A172: Ten | B172: 0 | C172: 20 | D172: 30 | E172: 50 | F172: 80
A173: Zetsu | B173: 0 | C173: 10 | D173: 20 | E173: 40 | F173: 70
A174: Ren | B174: 0 | C174: 20 | D174: 30 | E174: 50 | F174: 80
A175: Ken | B175: 0 | C175: 20 | D175: 30 | E175: 50 | F175: 80
A176: En | B176: 0 | C176: 20 | D176: 30 | E176: 50 | F176: 80
A177: Ko | B177: 0 | C177: 40 | D177: 50 | E177: 70 | F177: 100
A178: Ryu | B178: 0 | C178: 40 | D178: 50 | E178: 70 | F178: 100
A180: Base d'UAR par palier (état à manteau actif)
A181: Palier | B181: Base UAR
...

Sheet Référence
A1: RÉFÉRENCE — aide-mémoire (consultatif)
A3: Échelle de difficulté
A4: Palier | B4: Seuil
A5: Triviale | B5: 0
A6: Très facile | B6: 20
A7: Facile | B7: 40
A8: Moyenne | B8: 80
A9: Difficile | B9: 120
A10: Très difficile | B10: 180
A11: Absurde | B11: 240
A12: Quasi impossible | B12: 320
A13: Impossible | B13: 400
A14: Surhumaine | B14: 520
A15: Prodigieuse | B15: 640
A16: Insurmontable | B16: 780
A17: Inimaginable | B17: 920
A19: Types de dégâts (7)
A20: Sigle | B20: Nom | C20: Famille | D20: Exemples
A21: CON | B21: Contondant | C21: Physique | D21: Masses, poings, chutes
A22: TRA | B22: Tranchant | C22: Physique | D22: Lames, griffes, fil de Nen
A23: PER | B23: Perforant | C23: Physique | D23: Pointes, flèches, balles
A24: FEU | B24: Feu | C24: Élémentaire | D24: Feu, lave, vapeur
A25: FRO | B25: Froid | C25: Élémentaire | D25: Glace, gel
A26: ÉLE | B26: Électrique | C26: Élémentaire | D26: Foudre, décharges, lumière
A27: DÉC | B27: Décomposition | C27: Élémentaire | D27: Corruption, acide, ténèbres
A29: Marge (% de touche)
A30: Condition | B30: Effet
A31: ≥ 200 | B31: 200 % (×2, plafond)
A32: 10 à 199 | B32: ce % de touche
A33: 0 à 9 | B33: touche mais 0 dégât
A34: < 0 | B34: raté
A36: Postures de combat
A37: Posture | B37: Attaque | C37: Défense
A38: Défensive partielle | B38: −30 | C38: +10
A39: Défensive totale | B39: aucune att. | C39: +30
A40: Offensive partielle | B40: +10 | C40: −30
A41: Offensive totale | B41: +30 | C41: aucune déf.
A43: Situations
A44: Situation | B44: Init | C44: Att | D44: Esq | E44: Par | F44: Phys
A45: De dos | B45: – | C45: −30 | D45: −80 | E45: −80 | F45: –
A46: De flanc | B46: – | C46: −10 | D46: −30 | E46: −30 | F46: –
A47: En joue | B47: −50 | C47: −20 | D47: −120 | E47: −120 | F47: −100
A48: Espace réduit | B48: – | C48: −40 | D48: −40 | E48: −40 | F48: −20
A49: Surpris | B49: −120 | C49: – | D49: – | E49: – | F49: –
A53: États / afflictions (malus)
A54: État | B54: Effet
A55: Prise | B55: Agrippé / Maîtrisé / Soumis : saisi, mouvement 0 ; + Paralysie légère / partielle / totale
A56: Immobilisé | B56: entravé, mouvement 0 ; + Paralysie selon le degré
A57: Mutisme | B57: Léger : −80 compétences Vocales · Partiel : muet (sons ok) · Total : aucun son
A58: Paralysie légère | B58: −20 att/par/init ; −40 esq/phys
A59: Paralysie partielle | B59: −80 att/par/esq ; −30 init ; −60 phys
A60: Paralysie totale | B60: −200 att/par/esq/phys ; −100 init
A61: À terre | B61: −20 att ; contre lui +20 mêlée / −20 distance ; relever = 1 action
A62: Inconscience | B62: sans défense, touché automatiquement ; mêlée qui touche = critique ; tombe À terre
A63: Manœuvres (malus à l'attaque)
A64: Manœuvre | B64: Malus / effet
A65: Blesser | B65: 0 — seule manœuvre infligeant les dégâts
A66: Agripper | B66: −40 puis lutte → cible Agrippée
A67: Mettre à terre | B67: −40 puis lutte/équilibre → À terre
A68: Pousser | B68: −40 puis lutte/équilibre → repoussé 2 m+
A69: Désarmer | B69: −20 + Viser main (−60 à 1 main / −100 à 2 mains)
A70: Maîtriser / Soumettre | B70: pas de jet d'attaque (lutte opposée)
A72: Viser (malus à l'attaque par zone)
A73: Zone | B73: Malus
A74: Mollet / Torse | B74: −10
A75: Abdomen / Bras / Cuisse | B75: −20
A76: Épaule | B76: −30
A77: Main / Genou / Poignet | B77: −40
A78: Pied | B78: −50
A79: Tête / Coude / Cœur / Aine | B79: −60
A80: Cou | B80: −80
A81: Œil | B81: −100
A83: Catalogue d'armes (extrait — chaque arme vaut 100 points)
A84: Arme | B84: Dégâts faciaux | C84: Mod. | D84: Type | E84: Propriétés
A85: Mains nues | B85: 20 | C85: ×1 FOR | D85: CON | E85: Indésarmable
A86: Dague | B86: 30 | C86: ×1 | D86: PER | E86: Finesse, Dissimulable, jet 10/20 m
A87: Épée courte | B87: 40 | C87: ×1 | D87: TRA | E87: Finesse, Dégainage inst.
A88: Épée longue | B88: 30 (50) | C88: ×2 | D88: TRA | E88: Polyvalente
A89: Épée à 2 mains | B89: 50 | C89: ×3 | D89: TRA | E89: Lourde
A90: Sabre | B90: 40 (60) | C90: ×1 | D90: TRA | E90: Légère, Polyvalente
A91: Hache 1 main | B91: 40 (60) | C91: ×2 | D91: TRA | E91: Polyvalente
A92: Masse d'armes | B92: 20 | C92: ×2 | D92: CON | E92: Perce-blindage
A93: Lance | B93: 20 (40) | C93: ×2 | D93: PER | E93: Polyvalente, jet 10/20 m
A94: Bâton | B94: 20 (40) | C94: ×1 | D94: CON | E94: Polyvalente
A95: Fouet | B95: 0 | C95: ×1 | D95: CON | E95: Allonge ×3, Désarmement, Saisie
... A108: Sai / Jutte | B108: 60 | C108: ×1 | D108: CON | E108: Désarmement
A110: Toutes les valeurs proviennent du livre. Feuille purement consultative.
